augmix/__init__.py
augmix/augmix.py
augmix/helpers.py
augmix/transformations.py
augmix_tf-1.1.0.dist-info/LICENSE
augmix_tf-1.1.0.dist-info/METADATA
augmix_tf-1.1.0.dist-info/WHEEL
augmix_tf-1.1.0.dist-info/top_level.txt
augmix_tf-1.1.0.dist-info/RECORD
