Metadata-Version: 2.1
Name: augmix-tf
Version: 1.1.0
Summary: An implementation of novel data augmentation AugMix (2020) in TensorFlow. It runs on TPU.
Home-page: https://github.com/szacho/augmix-tf
Author: Michal Szachniewicz
Author-email: mszachniewicz@outlook.com
License: MIT
Platform: UNKNOWN
Classifier: License :: OSI Approved :: MIT License
Classifier: Programming Language :: Python :: 3
Classifier: Programming Language :: Python :: 3.7
Requires-Dist: tensorflow
Requires-Dist: tensorflow-probability
